nosescript/unit.py
nosescript/__init__.py
nosescript/test_assertions.py
nosescript/loader.py
nosescript/tests/run_me_not.js
nosescript/tests/test_qunit_exceptions.js
nosescript/tests/test_mod.js
nosescript/tests/test_qunit_common.js
nosescript/tests/reqs/consts.js
nosescript/bridge/__init__.py
nosescript/bridge/qunit.py
nosescript/resources/__init__.py
nosescript/resources/json2.js
nosescript/resources/qunit-api.js
nosescript-0.1.0.dist-info/METADATA
nosescript-0.1.0.dist-info/entry_points.txt
nosescript-0.1.0.dist-info/RECORD
nosescript-0.1.0.dist-info/top_level.txt
nosescript-0.1.0.dist-info/WHEEL
nosescript-0.1.0.dist-info/DESCRIPTION.rst
nosescript-0.1.0.dist-info/metadata.json
