Metadata-Version: 2.0
Name: nosescript
Version: 0.1.0
Summary: A Nose plugin for JavaScript tests.
Home-page: https://github.com/simpoir/nosescript
Author: Simon Poirier
Author-email: simpoir+nosescript@gmail.com
License: MIT
Platform: UNKNOWN
Classifier: Development Status :: 2 - Pre-Alpha
Classifier: Environment :: Plugins
Classifier: Intended Audience :: Developers
Classifier: License :: OSI Approved :: MIT License
Classifier: Programming Language :: Python :: 2
Classifier: Programming Language :: Python :: 2.7
Classifier: Topic :: Software Development :: Testing
Requires-Dist: nose
Requires-Dist: python-spidermonkey
